{
  "quality_fixed": true,
  "title": "The Art of Clear Communication",
  "subtitle": "Mastering the skill that underlies all success in work and relationships",
  "premise": "A comprehensive exploration of how clear communication is not an innate talent but a learnable, deliberate discipline that is critical to professional success, personal fulfillment, and functional relationships.",
  "core_message": "Clear communication is the ultimate force multiplier—it transforms individual competence into collective achievement, converts strategy into action, bridges the gap between intention and understanding, and is the foundational infrastructure upon which all success and connection are built.",
  "total_chapters": 10,
  "target_audience": {
    "primary": "Professionals, leaders, and anyone seeking to improve their communication skills",
    "secondary": "Teams, managers, educators, and individuals in any relationship context",
    "impact_focus": "Anyone who aspires to lead, collaborate, or connect effectively in our complex world"
  },
  "chapters": [
    {
      "number": 1,
      "title": "The High Cost of Miscommunication: Why Clarity Isn't Optional",
      "key_themes": [
        "The $62.4 million annual cost per organization due to inadequate communication",
        "Financial and operational impacts of miscommunication",
        "Human and personal costs of unclear communication",
        "The digital age amplification of miscommunication",
        "Clarity as kindness and respect"
      ],
      "core_concepts": [
        "Miscommunication drains financial resources, erodes trust, stifles innovation, fuels conflict",
        "Project failure often traces to ineffective communication",
        "Employee engagement directly correlates with clarity of expectations",
        "Conflict stems from mismatched expectations, unspoken assumptions, and misinterpreted tones",
        "Technical expertise without communication ability limits career growth",
        "Clear communication is 85% of financial success"
      ],
      "supporting_statistics": [
        "$62.4 million average annual loss per organization to miscommunication",
        "Nearly 1/3 of failed projects linked to ineffective communication",
        "52% of respondents report increased stress from poor communication",
        "44% experience failure to complete projects due to poor communication",
        "85% of financial success attributed to 'human engineering' skills"
      ],
      "key_arguments": [
        "Clarity is not optional—it is a hard, economic imperative",
        "Communication costs manifest at macroeconomic, operational, and personal scales",
        "The digital age has exponentially amplified both the necessity for clarity and potential for misunderstanding",
        "Clarity is learnable and can be broken down into components, practiced, and mastered"
      ]
    },
    {
      "number": 2,
      "title": "The Listener's Mind: Understanding How Your Message is Received",
      "key_themes": [
        "The brain is a prediction engine, not a passive recording device",
        "Cognitive biases shape message reception",
        "Working memory limitations affect comprehension",
        "Audience analysis precedes message crafting",
        "Dialogue over monologue for effective communication"
      ],
      "core_concepts": [
        "The brain predicts meaning 250 milliseconds before the speaker finishes",
        "Curse of knowledge: experts underestimate what novices don't know",
        "Confirmation bias: listeners filter information through existing beliefs",
        "Affect heuristic: emotional state colors rational processing",
        "Cognitive load: working memory holds only 4-7 discrete chunks",
        "Listener's physical and psychological state dramatically affects reception"
      ],
      "cognitive_biases_covered": [
        "Curse of knowledge",
        "Confirmation bias",
        "Affect heuristic",
        "Cognitive load theory",
        "Inattentional blindness"
      ],
      "techniques_introduced": [
        "Audience analysis: understanding listener's prior knowledge and biases",
        "Analogy and metaphor: linking new to known",
        "Framing: establishing context for interpretation",
        "Structure: providing narrative and hierarchy",
        "Feedback and co-creation: collaborative confirmation"
      ],
      "key_principle": "Your clarity is defined not by your intent, but by the listener's comprehension"
    },
    {
      "number": 3,
      "title": "The Architecture of a Clear Thought: From Internal Idea to External Message",
      "key_themes": [
        "Thinking about what to communicate, not just what to say",
        "Distillation of dense internal knowledge into communicable ideas",
        "Structure is not aesthetic—it is a cognitive necessity",
        "Translating internal thought to external language",
        "The bridge between idea and language"
      ],
      "core_concepts": [
        "Knowledge condensation: internal ideas exist as multidimensional networks",
        "First-Principles Clarification: interrogating your own concept before audience communication",
        "Strategic exclusion: select only load-bearing elements",
        "Pyramid Principle: lead with answer, follow with arguments, then data",
        "Concreteness Over Abstraction: replace vague nouns with specific terms",
        "Metadiscourse: explicit signaling of message structure"
      ],
      "architectural_process": [
        "Define core objective in one simple sentence",
        "Select supporting material through strategic exclusion",
        "Sequence content to serve the objective, not chronologically",
        "Translate to concrete language and specific metrics",
        "Use analogy and metaphor to bridge abstraction",
        "Signal structure explicitly with metadiscourse",
        "Externalize through appropriate medium (spoken, written, visual)"
      ],
      "key_framework": "Pyramid Principle—lead with conclusion, support with arguments, detail with facts",
      "critical_statistic": "72% of leaders who articulated core objective in one sentence were rated effective"
    },
    {
      "number": 4,
      "title": "The Precision Toolbox: Choosing the Exact Right Word and Structure",
      "key_themes": [
        "Individual word choice carries immense weight",
        "Sentence structure determines clarity and impact",
        "Parallel structure aids cognitive processing",
        "Information ordering mirrors natural attention flow",
        "Verbal economy intensifies message potency"
      ],
      "core_concepts": [
        "Diction: precise word choice maps to intended concept",
        "Abstraction ladders: moving from abstract to concrete",
        "Subject-verb-object structure: clear actor-action relationships",
        "Nominalizations: burying action in nouns obscures meaning",
        "Parallel structure: matching grammatical patterns for patterned ideas",
        "Given-before-new principle: anchor with familiar, deliver new at end",
        "Topic sentences: contracts with readers about paragraph direction",
        "Inverted pyramid: front-load importance, follow with details"
      ],
      "linguistic_tools": [
        "Active voice over passive voice",
        "Strong, specific verbs over weak nominalizations",
        "Concrete nouns over abstract language",
        "Parallel lists and structures",
        "Given-before-new information ordering",
        "Concision: eliminating redundancy and empty modifiers"
      ],
      "key_distinction": "Precision is defined not by vocabulary sophistication but by minimizing interpretive wiggle room",
      "supporting_research": "Documents revised for active voice and strong verbs showed 40% increase in recall, 33% decrease in comprehension time"
    },
    {
      "number": 5,
      "title": "Beyond Words: Mastering Tone, Pace, and Nonverbal Signals",
      "key_themes": [
        "Paralanguage: tone, pitch, volume, pace, rhythm, pauses",
        "Nonverbal communication outweighs words in emotional meaning",
        "Congruence: alignment of verbal, vocal, and visual channels",
        "Adaptation to digital channels strips nonverbal signals",
        "Active listening extends to decoding nonverbal cues"
      ],
      "core_concepts": [
        "Mehrabian model: 7% words, 38% vocal, 55% nonverbal",
        "Vocal tone: emotional quality received by brain's right hemisphere first",
        "Pace and pause: tempo and silence as tools for comprehension and emphasis",
        "Posture and gesture: framework of physical presence",
        "Facial expressions and eye contact: most scrutinized channels",
        "Proxemics and haptics: space and touch as communication",
        "Congruence: unified message across all channels",
        "Incongruence: primary engine of misunderstanding and mistrust"
      ],
      "paralanguage_elements": [
        "Pitch: emotional quality and attitude",
        "Tone: emotional coloring of speech",
        "Volume: emphasis and intensity",
        "Pace: speed affecting cognitive load",
        "Rhythm: pattern of speech flow",
        "Pauses: silence before emphasis or to allow processing"
      ],
      "nonverbal_channels": [
        "Posture: confidence and receptivity signals",
        "Gestures: punctuation marks of physical communication",
        "Facial expressions: authenticity and emotional content",
        "Eye contact: connection, honesty, and attentiveness",
        "Personal space: proxemics and comfort boundaries",
        "Touch: high-risk channel in professional contexts"
      ],
      "key_principle": "Congruence closes gap between intention and interpretation",
      "digital_adaptation": "Compensatory strategies for text-based communication lacking paralanguage"
    },
    {
      "number": 6,
      "title": "The Art of the Question: Unlocking Understanding and Dialogue",
      "key_themes": [
        "Questions are the master key to genuine understanding",
        "Strategic inquiry shapes cognitive activity of respondents",
        "Building psychological safety through curious questioning",
        "Different question types serve different conversational objectives",
        "Culture of inquiry drives innovation and learning"
      ],
      "core_concepts": [
        "Brain's default mode network activated by complex questions",
        "Questions build rapport more effectively than statements",
        "Follow-up questions demonstrate careful listening and engagement",
        "Psychological safety: shared belief that team is safe for risk-taking",
        "Question types: diagnostic, strategic, empathetic, clarifying",
        "Assumption of understanding leads to misalignment",
        "Five Whys: iterative questioning to uncover root causes",
        "Interest-based dialogue: excavating underlying needs vs. stated positions"
      ],
      "question_types": {
        "diagnostic": "Uncovering root causes and systemic issues ('Why' and 'How' framed carefully)",
        "strategic": "Future-oriented and expansive ('If we had no constraints...')",
        "empathetic": "Prioritizing emotional data ('How does it feel...')",
        "clarifying": "Eliminating ambiguity in abstract language ('When you say soon...')"
      },
      "techniques": [
        "Playback/check for understanding",
        "Five Whys methodology",
        "Socratic leadership: guiding discovery",
        "Pre-mortems: imagining failure to identify risks",
        "After-action reviews: learning loops"
      ],
      "research_finding": "Teams with high levels of inquiry show 30% higher innovation rates and lower turnover",
      "ultimate_purpose": "Questioning is intellectual humility and respect for the other's perspective"
    },
    {
      "number": 7,
      "title": "Navigating Difficult Conversations: Clarity in Conflict and Feedback",
      "key_themes": [
        "Physiological responses undermine clear communication in conflict",
        "Separating observation from evaluation prevents defensiveness",
        "Feedback structures map observations to behavioral impacts",
        "Articulating interests unlocks creative problem-solving",
        "Language precision de-escalates conflict"
      ],
      "core_concepts": [
        "Amygdala threat response narrows cognition in conflict",
        "Physiological regulation (breathing) enables clearer communication",
        "Observation vs. evaluation: fact-based vs. judgmental framing",
        "SBI Framework: Situation-Behavior-Impact structure",
        "Receiving feedback as information gathering, not self-defense",
        "Position vs. interest: stated demand vs. underlying need",
        "Us-versus-problem framing: collaborative approach",
        "Emotional subtext: acknowledging feelings beneath surface",
        "Specific agreements: eliminating forward-looking ambiguity"
      ],
      "feedback_framework": "SBI—Situation (specific), Behavior (observable), Impact (consequence)",
      "conflict_tools": [
        "Physiological regulation before difficult conversation",
        "Observation-only descriptions before interpretation",
        "Interest articulation and exploration",
        "Emotional acknowledgment",
        "Problem-focused language over person-focused blame",
        "Specific, detailed agreements and follow-up protocols"
      ],
      "key_principle": "Clear communication in conflict transforms costly encounters into engines of growth and trust",
      "cost_of_conflict": "$359 billion in paid hours lost annually in the United States to workplace conflict"
    },
    {
      "number": 8,
      "title": "The Digital Dilemma: Achieving Clarity Without Tone of Voice",
      "key_themes": [
        "Digital communication strips 93% of emotional signal",
        "Text-based ambiguity creates costly misunderstanding",
        "Structural empathy compensates for lost paralanguage",
        "Metacommunication explicitly labels intent",
        "Visual and grammatical warmth simulate vocal presence"
      ],
      "core_concepts": [
        "Signal loss: 7% words, 38% vocal, 55% nonverbal lost in text",
        "Affective forecasting: brain fills void with projections and biases",
        "Communication debt: accumulating weight of unresolved ambiguities",
        "Structural empathy: architecting message with recipient's context",
        "Metacommunication: communicating about the communication",
        "Precision: eliminating vague temporals and abstract terms",
        "Visual warmth: paragraph breaks, white space, bolding",
        "Grammatical tone: active voice, concrete nouns, appropriate formality",
        "Channel intentionality: synchronous for difficult, asynchronous for routine",
        "Shared protocols: explicit team norms for digital communication"
      ],
      "compensation_strategies": [
        "Front-load context and frame",
        "Use explicit metacommunication markers",
        "Replace vague language with specifics",
        "Structure visually for scannability",
        "Use active voice and strong verbs",
        "Establish team communication protocols"
      ],
      "guideline": "Video for high-stakes conversations, written for documentation and routine updates",
      "research": "High-performing teams 76% more likely to use explicit metacommunication in digital exchanges",
      "platinum_rule": "Communicate with others how they prefer for high-stakes matters"
    },
    {
      "number": 9,
      "title": "Persuasion Through Precision: Structuring Arguments That Resonate",
      "key_themes": [
        "Brilliance obscured by poor architecture remains invisible",
        "Structural presentation is 73% more predictive of adoption than idea strength",
        "Problem-Agitation-Solution provides robust macro-architecture",
        "Logical linking connects claims to evidence transparently",
        "Framing aligns argument with audience values and language"
      ],
      "core_concepts": [
        "Data-dump approach creates cognitive chaos",
        "Pattern-seeking brain needs clear, logical scaffold",
        "Problem-Agitation-Solution: clinical problem definition, consequence exploration, direct solution",
        "Loss aversion: motivated more to avoid losses than acquire gains",
        "Logical linking: explicit bridge between evidence and claims",
        "Refutational preemption: addressing counterarguments proactively",
        "Framing: metaphors and concepts determine acceptability",
        "Call to Action: specific, behavioral, time-bound, responsibility-assigned"
      ],
      "persuasive_framework": "Problem-Agitation-Solution (PAS)",
      "problem_phase": "Define issue with clinical specificity, avoiding vague generalities",
      "agitation_phase": "Explore consequences of inaction, leveraging loss aversion",
      "solution_phase": "Present as direct, logical, proportionate response to agitation",
      "micro_architecture": [
        "Logical linking: transparent bridges between claims and evidence",
        "Refutational preemption: voice strongest objections within argument",
        "Framing: use audience's strategic language and values",
        "Call to Action: specific next step with timeline and responsibility"
      ],
      "key_statistic": "89% believed idea strength was primary factor; actually structural presentation was 73% more predictive",
      "design_principle": "Persuasion is structural science, not charismatic art"
    },
    {
      "number": 10,
      "title": "The Communicator's Loop: Integrating Listening and Speaking for Continuous Improvement",
      "key_themes": [
        "Communication is a dynamic, self-correcting loop, not linear transmission",
        "Diagnostic listening interprets multiple concurrent information streams",
        "Strategic pause between listening and speaking integrates synthesis",
        "Calibrated speaking adapts in real-time to diagnostic data",
        "Feedback-seeking closes the loop and enables iteration"
      ],
      "core_concepts": [
        "Formulation gap: brain prepares speech while listening",
        "Diagnostic listening: analyzing underlying architecture of perspective",
        "Paraphrasing for validation: probing boundaries, confirming understanding",
        "Synthesis: integrating information with personal knowledge and goals",
        "Strategic pause: conscious cognitive workspace (1-2 seconds optimal)",
        "Calibrated speaking: output adjusted based on diagnostic data",
        "Message elasticity: adapting core message without losing essence",
        "Feedback-seeking: soliciting data on output effectiveness",
        "Communication agility: real-time adjustment based on feedback",
        "Interactive synchrony: rapid, adaptive turn-taking"
      ],
      "four_phases": {
        "phase_1_diagnostic_listening": "Data collection analyzing explicit content and structural/emotional substrate",
        "phase_2_synthesis_and_pause": "Processing and integrating information with conscious 1-2 second pause",
        "phase_3_calibrated_speaking": "Delivering response adapted to listener's inferred state and needs",
        "phase_4_feedback_seeking": "Actively soliciting data on message impact through questions and observation"
      ],
      "techniques": [
        "Listen for presuppositions embedded in language",
        "Paraphrase to probe and confirm understanding",
        "Utilize strategic pause for thoughtful processing",
        "Calibrate vocabulary, tone, pace, and complexity to listener state",
        "Seek feedback explicitly: 'How would you summarize the next step?'",
        "Read and decode nonverbal cues for real-time adjustment",
        "Adapt mid-stream when logic fails to land or eyes glaze over"
      ],
      "key_benefit": "Communication Agility—real-time capacity to adjust approach based on feedback",
      "research": "High-performing teams showed interactive synchrony accounting for 35% of productivity variance",
      "ultimate_goal": "Transform communication from linear transmission to continuous, improving loop of dialogue"
    }
  ],
  "key_themes_across_book": [
    "Communication is a learnable, deliberate discipline, not innate talent",
    "Clarity is kindness—it respects and empowers the listener",
    "The listener's interpretation defines success, not the speaker's intent",
    "Structure is as important as content for comprehension",
    "Empathy and precision are married disciplines",
    "Dialogue and feedback loops are essential for understanding",
    "Context and audience analysis precede all communication",
    "Technical expertise without communication ability is self-limiting",
    "Congruence across channels builds trust",
    "Cost of poor communication is quantifiable and enormous",
    "Clear communication transforms conflicts into growth opportunities"
  ],
  "critical_statistics": {
    "financial_cost": "$62.4 million average annual loss per organization due to miscommunication",
    "project_failure_rate": "Nearly 1/3 of projects fail due to ineffective communication",
    "employee_engagement": "Clarity of expectations is among the strongest predictors of engagement",
    "financial_success_attribution": "85% of financial success attributed to human engineering (communication) skills",
    "brain_prediction_speed": "Brain predicts meaning 250 milliseconds before speaker finishes",
    "digital_communication_penetration": "95% of knowledge workers rely on digital written communication as primary mode",
    "weekly_misunderstanding_rate": "72% of professionals report misunderstanding from digital messages at least once weekly",
    "conflict_cost": "$359 billion in paid hours lost to workplace conflict in the US annually",
    "meta_finding": "Structural presentation 73% more predictive of idea adoption than strength of idea"
  },
  "methodologies_and_frameworks": [
    "Pyramid Principle (Barbara Minto)",
    "SBI Framework: Situation-Behavior-Impact",
    "Problem-Agitation-Solution (PAS)",
    "Nonviolent Communication (Marshall Rosenberg)",
    "Principled Negotiation (Roger Fisher, William Ury)",
    "Five Whys",
    "Socratic Leadership",
    "Abstraction Ladders (S.I. Hayakawa)",
    "Given-before-new Principle",
    "Inverted Pyramid (Journalism)",
    "The Communicator's Loop",
    "Diagnostic Listening",
    "Strategic Framing",
    "Message Elasticity",
    "Interactive Synchrony"
  ],
  "supporting_research_sources": [
    "Journal of Business and Psychology",
    "Project Management Institute - Pulse of the Profession",
    "Harvard Business Review",
    "University of California, Berkeley - Communication Neuroscience",
    "Economist Intelligence Unit",
    "Gallup Research on Employee Engagement",
    "Carnegie Institute of Technology",
    "Daniel Kahneman - Judgment and Decision-Making",
    "MIT Human Dynamics Laboratory",
    "Google's Project Aristotle",
    "Center for Creative Leadership",
    "Harvard Law School - Project on Negotiation",
    "Pew Research Center",
    "McKinsey Global Institute",
    "OECD Policy Brief Analysis"
  ],
  "reading_journey": {
    "foundation": "Chapters 1-2: Understanding the problem and the listener's mind",
    "core_skills": "Chapters 3-5: Building clear thoughts, precise language, and integrated delivery",
    "advanced_applications": "Chapters 6-7: Mastering questions and difficult conversations",
    "specialized_contexts": "Chapters 8-9: Navigating digital communication and persuasive structure",
    "integration": "Chapter 10: Synthesizing all skills into a continuous feedback loop"
  },
  "practical_takeaways_by_context": {
    "leadership": [
      "Use diagnostic listening to understand team's actual concerns",
      "Structure feedback with SBI framework",
      "Foster culture of inquiry through Socratic questioning",
      "Build psychological safety through curiosity and vulnerability"
    ],
    "team_collaboration": [
      "Establish shared digital communication protocols",
      "Use Problem-Agitation-Solution to present initiatives",
      "Practice diagnostic listening in meetings",
      "Implement after-action reviews for continuous improvement"
    ],
    "conflict_resolution": [
      "Regulate physiology before difficult conversations",
      "Separate observation from evaluation",
      "Articulate interests, not just positions",
      "Create specific agreements with forward-looking clarity"
    ],
    "presentation_and_persuasion": [
      "Lead with core objective or conclusion",
      "Use analogies to make abstract concrete",
      "Structure arguments as Problem-Agitation-Solution",
      "End with specific, time-bound Call to Action"
    ],
    "digital_communication": [
      "Use structural empathy when writing remotely",
      "Add explicit metacommunication markers for tone",
      "Replace vague language with specifics",
      "Reserve video calls for high-stakes conversations"
    ],
    "personal_relationships": [
      "Cultivate curiosity through strategic questioning",
      "Practice diagnostic listening to understand deeper concerns",
      "Articulate needs and desires clearly",
      "Seek regular feedback on impact of communication"
    ]
  }
}
